resdag/__init__.py
resdag/composition/__init__.py
resdag/composition/symbolic.py
resdag/hpo/__init__.py
resdag/hpo/losses.py
resdag/hpo/objective.py
resdag/hpo/run.py
resdag/hpo/utils.py
resdag/init/__init__.py
resdag/init/graphs/__init__.py
resdag/init/graphs/barabasi_albert.py
resdag/init/graphs/chord_dendrocycle.py
resdag/init/graphs/complete.py
resdag/init/graphs/connected_erdos_renyi.py
resdag/init/graphs/connected_watts_strogatz.py
resdag/init/graphs/dendrocycle.py
resdag/init/graphs/erdos_renyi.py
resdag/init/graphs/kleinberg_small_world.py
resdag/init/graphs/multi_cycle.py
resdag/init/graphs/newman_watts_strogatz.py
resdag/init/graphs/random.py
resdag/init/graphs/regular.py
resdag/init/graphs/ring_chord.py
resdag/init/graphs/simple_cycle_jumps.py
resdag/init/graphs/spectral_cascade.py
resdag/init/graphs/watts_strogatz.py
resdag/init/graphs/zero.py
resdag/init/input_feedback/__init__.py
resdag/init/input_feedback/base.py
resdag/init/input_feedback/binary_balanced.py
resdag/init/input_feedback/chain_of_neurons_input.py
resdag/init/input_feedback/chebyshev.py
resdag/init/input_feedback/chessboard.py
resdag/init/input_feedback/dendrocycle_input.py
resdag/init/input_feedback/opposite_anchors.py
resdag/init/input_feedback/pseudo_diagonal.py
resdag/init/input_feedback/random.py
resdag/init/input_feedback/random_binary.py
resdag/init/input_feedback/registry.py
resdag/init/input_feedback/ring_window.py
resdag/init/input_feedback/zero.py
resdag/init/topology/__init__.py
resdag/init/topology/base.py
resdag/init/topology/registry.py
resdag/init/utils/__init__.py
resdag/init/utils/graph_tools.py
resdag/init/utils/resolve.py
resdag/layers/__init__.py
resdag/layers/reservoir.py
resdag/layers/custom/__init__.py
resdag/layers/custom/concatenate.py
resdag/layers/custom/feature_partitioner.py
resdag/layers/custom/outliers_filtered_mean.py
resdag/layers/custom/selective_dropout.py
resdag/layers/custom/selective_exponentiation.py
resdag/layers/readouts/__init__.py
resdag-0.2.0.dist-info/METADATA
resdag-0.2.0.dist-info/WHEEL
resdag-0.2.0.dist-info/RECORD
