Metadata-Version: 2.4
Name: resdag
Version: 0.2.0
Summary: PyTorch-native reservoir computing library with GPU acceleration
Project-URL: Homepage, https://github.com/El3ssar/resdag
Project-URL: Repository, https://github.com/El3ssar/resdag
Project-URL: Issues, https://github.com/El3ssar/resdag/issues
Author-email: Daniel Estevez-Moya <kemossabee@gmail.com>
License-Expression: MIT
Keywords: echo state networks,machine learning,pytorch,reservoir computing
Classifier: Development Status :: 3 - Alpha
Classifier: Intended Audience :: Science/Research
Classifier: License :: OSI Approved :: MIT License
Classifier: Programming Language :: Python :: 3
Classifier: Programming Language :: Python :: 3.9
Classifier: Programming Language :: Python :: 3.10
Classifier: Programming Language :: Python :: 3.11
Classifier: Programming Language :: Python :: 3.12
Classifier: Topic :: Scientific/Engineering :: Artificial Intelligence
Requires-Python: >=3.11
Requires-Dist: basedpyright>=1.37.1
Requires-Dist: graphviz>=0.21
Requires-Dist: networkx>=3.0
Requires-Dist: numpy>=2.4.0
Requires-Dist: pytorch-symbolic>=1.1.1
Requires-Dist: scipy>=1.17.0
Requires-Dist: torch>=2.9.1
Provides-Extra: dev
Requires-Dist: black>=25.12.0; extra == 'dev'
Requires-Dist: mypy>=1.0.0; extra == 'dev'
Requires-Dist: optuna>=4.0.0; extra == 'dev'
Requires-Dist: pytest-cov>=4.0.0; extra == 'dev'
Requires-Dist: pytest>=9.0.2; extra == 'dev'
Requires-Dist: ruff>=0.14.10; extra == 'dev'
Provides-Extra: hpo
Requires-Dist: optuna>=3.0.0; extra == 'hpo'
